Workbook

Sheet GUIA DE USO
A1: GUIA DE USO - SISTEMA FINANCIERO PERSONAL
A2: Sistema para el control integral de finanzas personales y profesionales | Inicio: Junio 2026
A4: COMO CAMBIAR EL INGRESO MENSUAL
A5: PASO 1: Ve a la pestana 'PRESUPUESTO MENSUAL' (tercera pestana del libro)
A6: PASO 2: Localiza la celda D3 — tiene fondo AMARILLO/DORADO y letra grande
A7: PASO 3: Haz doble clic en D3 y escribe tu nuevo ingreso neto mensual
A8: PASO 4: Pulsa ENTER — todo el sistema se actualiza automaticamente
A10: NOTA IMPORTANTE: La celda D3 de PRESUPUESTO MENSUAL es el unico valor que debes
A11: cambiar cada mes. Todos los calculos del sistema usan ese valor como referencia.
A13: DESCRIPCION DE LAS HOJAS DEL SISTEMA
A14: Hoja | B14: Descripcion y uso
A15: DASHBOARD EJECUTIVO | B15: Panel principal con todos los KPIs financieros.
A16: REGISTRO DE MOVIMIENTOS | B16: Registra TODOS tus ingresos y gastos. Es la hoja mas importante.
A17: PRESUPUESTO MENSUAL | B17: Define tu presupuesto. Introduce el ingreso en D3 (celda dorada).
A18: CONTROL DE AHORRO | B18: Registra aportaciones al ahorro mensual.
A19: CONTROL DE BANKROLL | B19: Registra aportaciones al bankroll de trading (10% del ingreso).
A20: DASHBOARD DE TRADING | B20: Registra resultados de trading. Calcula ROI y evolucion.
A21: CONTROL DE PAYOUTS | B21: Registra pagos recibidos de plataformas de trading.
A22: PATRIMONIO NETO | B22: Calcula tu patrimonio neto (Activos - Pasivos).
A23: FONDO DE EMERGENCIA | B23: Controla el progreso hacia tu fondo de emergencia.
A24: OBJETIVOS | B24: Define y sigue el progreso de tus objetivos financieros anuales.
A25: GASTOS HORMIGA | B25: Registra gastos pequenos recurrentes. Detecta fugas de dinero.
... A29: SCORE DEL TRADER | B29: Puntuacion 0-100 que evalua tu desempeno financiero.
A31: LEYENDA DE COLORES
A32: VERDE: Indicador positivo / objetivo cumplido / dentro de presupuesto
A33: DORADO: Subtitulos, totales y valores destacados (tambien la celda de ingreso D3)
A34: ROJO: Alerta / presupuesto excedido / objetivo no alcanzado
A35: AZUL OSCURO: Cabeceras de tablas y secciones principales
A36: GRIS: Cabeceras de columnas
A37: GRIS CLARO: Filas alternas para mejor legibilidad

Sheet DASHBOARD EJECUTIVO
A1: DASHBOARD EJECUTIVO - SISTEMA FINANCIERO PERSONAL 2026
A2: Sistema de control financiero integral | Inicio: Junio 2026 | Referencia: 2.000 EUR/mes
A3: INGRESO MENSUAL: Para cambiar el ingreso ve a la hoja 'PRESUPUESTO MENSUAL' y edita la celda D3 (dorada)
A5: KPIs PRINCIPALES - JUNIO 2026
A6: Ingreso del Mes (D3 PRESUPUESTO) | C6: Gastos Totales (Movimientos) | E6: Flujo de Caja | G6: Ahorro Mensual | I6: Ahorro Acumulado | K6: Bankroll Capital
A7: ='PRESUPUESTO MENSUAL'!$D$3 | C7: =SUMIF('REGISTRO DE MOVIMIENTOS'!D3:D1000,"Gasto",'REGISTRO DE MOVIMIENTOS'!H3:H1000) | E7: ='PRESUPUESTO MENSUAL'!$D$3-SUMIF('REGISTRO DE MOVIMIENTOS'!D3:D1000,"Gasto",'REGISTRO DE MOVIMIENTOS'!H3:H1000) | G7: ='CONTROL DE AHORRO'!D3 | I7: =MAX('CONTROL DE AHORRO'!E3:E1000) | K7: =MAX('CONTROL DE BANKROLL'!E3:E1000)
A9: Benef. Trading Mes | C9: Payouts Cobrados | E9: Patrimonio Neto | G9: ROI Trading % | I9: Score Financiero /100 | K9: Libertad Financiera %
A10: =SUM('DASHBOARD DE TRADING'!C3:C1000) | C10: =SUMIF('CONTROL DE PAYOUTS'!D3:D1000,"Cobrado",'CONTROL DE PAYOUTS'!C3:C1000) | E10: ='PATRIMONIO NETO'!B20 | G10: =IFERROR(SUM('DASHBOARD DE TRADING'!C3:C1000)/MAX('CONTROL DE BANKROLL'!E3:E1000),0) | I10: ='SCORE DEL TRADER'!D10 | K10: ='LIBERTAD FINANCIERA'!B5
A13: RESUMEN PRESUPUESTARIO MENSUAL
A14: Concepto | C14: Importe | E14: % Ingreso
A15: Ingreso Neto (PRESUPUESTO MENSUAL D3) | C15: ='PRESUPUESTO MENSUAL'!$D$3 | E15: =C15/'PRESUPUESTO MENSUAL'!$D$3
A16: Gastos Fijos | C16: =1575 | E16: =C16/'PRESUPUESTO MENSUAL'!$D$3
A17: Bankroll (10%) | C17: ='PRESUPUESTO MENSUAL'!$D$3*0.1 | E17: =C17/'PRESUPUESTO MENSUAL'!$D$3
A18: Ahorro (10%) | C18: ='PRESUPUESTO MENSUAL'!$D$3*0.1 | E18: =C18/'PRESUPUESTO MENSUAL'!$D$3
A19: Caprichos (5%) | C19: ='PRESUPUESTO MENSUAL'!$D$3*0.05 | E19: =C19/'PRESUPUESTO MENSUAL'!$D$3
A20: DISPONIBLE | C20: ='PRESUPUESTO MENSUAL'!$D$3-1575-'PRESUPUESTO MENSUAL'!$D$3*0.25 | E20: =C20/'PRESUPUESTO MENSUAL'!$D$3
A22: NAVEGACION: Usa las pestanas de abajo para acceder a cada seccion del sistema

Sheet REGISTRO DE MOVIMIENTOS
A1: REGISTRO DE MOVIMIENTOS - SISTEMA FINANCIERO 2026
A2: Fecha | B2: Mes | C2: Anio | D2: Tipo | E2: Categoria | F2: Subcategoria | G2: Descripcion | H2: Importe | I2: Metodo de Pago | J2: Comentarios
A3: 46174 | B3: Junio | C3: 2026 | D3: Ingreso | E3: Nomina | F3: Salario neto | G3: Salario neto junio 2026 | H3: 2000 | I3: Transferencia | J3: Ingreso mensual regular
A4: 46174 | B4: Junio | C4: 2026 | D4: Gasto | E4: Vivienda | F4: Alquiler | G4: Piso alquiler junio | H4: 1000 | I4: Transferencia | J4: Gasto fijo
A5: 46174 | B5: Junio | C5: 2026 | D5: Gasto | E5: Transporte | F5: Coche | G5: Cuota coche junio | H5: 450 | I5: Domiciliacion | J5: Gasto fijo
A6: 46174 | B6: Junio | C6: 2026 | D6: Gasto | E6: Salud/Deporte | F6: Gimnasio | G6: Cuota gimnasio junio | H6: 25 | I6: Domiciliacion | J6: Gasto fijo
A7: 46174 | B7: Junio | C7: 2026 | D7: Gasto | E7: Formacion | F7: TraderLab | G7: Suscripcion TraderLab junio | H7: 100 | I7: Tarjeta | J7: Gasto fijo
A8: 46178 | B8: Junio | C8: 2026 | D8: Gasto | E8: Alimentacion | F8: Supermercado | G8: Compra semanal Mercadona | H8: 85.5 | I8: Tarjeta
A9: 46183 | B9: Junio | C9: 2026 | D9: Gasto | E9: Restaurantes | F9: Comida fuera | G9: Restaurante con familia | H9: 35 | I9: Tarjeta | J9: Gasto capricho
A10: 46188 | B10: Junio | C10: 2026 | D10: Ingreso | E10: Trading | F10: Payout | G10: Payout FTMO junio | H10: 350 | I10: Transferencia | J10: Beneficios trading
A11: 46193 | B11: Junio | C11: 2026 | D11: Gasto | E11: Ahorro | F11: Ahorro mensual | G11: Aportacion ahorro junio | H11: 200 | I11: Transferencia | J11: 10% ingreso mensual
A12: 46193 | B12: Junio | C12: 2026 | D12: Gasto | E12: Inversion | F12: Bankroll | G12: Aportacion bankroll junio | H12: 200 | I12: Transferencia | J12: 10% ingreso mensual

Sheet PRESUPUESTO MENSUAL
A1: PRESUPUESTO MENSUAL - JUNIO 2026
A3: Ingreso neto mensual - MODIFICA AQUI CADA MES: | D3: 2000
A4: >>> ESTA ES LA CELDA CLAVE: cambia D3 cada mes y todo el sistema se actualiza <<<
A6: GASTOS FIJOS MENSUALES
A7: Concepto | B7: Categoria | C7: Importe | D7: % Ingreso | E7: Estado
A8: Piso | B8: Vivienda | C8: 1000 | D8: =C8/$D$3 | E8: Fijo
A9: Coche | B9: Transporte | C9: 450 | D9: =C9/$D$3 | E9: Fijo
A10: Gimnasio | B10: Salud/Deporte | C10: 25 | D10: =C10/$D$3 | E10: Fijo
A11: TraderLab | B11: Formacion | C11: 100 | D11: =C11/$D$3 | E11: Fijo
A12: TOTAL GASTOS FIJOS | C12: =SUM(C8:C11) | D12: =C12/$D$3
A14: DISTRIBUCION AUTOMATICA (% INGRESO)
A15: Concepto | B15: % Aplicado | C15: Importe | D15: Objetivo anual | E15: Descripcion
A16: Bankroll | B16: 0.1 | C16: =$D$3*B16 | D16: =$D$3*B16*12 | E16: 10% para capital de trading
A17: Ahorro | B17: 0.1 | C17: =$D$3*B17 | D17: =$D$3*B17*12 | E17: 10% para fondo de ahorro
A18: Caprichos | B18: 0.05 | C18: =$D$3*B18 | D18: =$D$3*B18*12 | E18: 5% para gastos personales
A20: RESUMEN Y DISPONIBLE
A21: Concepto | C21: Importe
A22: Ingreso neto mensual | C22: =$D$3
A23: (-) Total gastos fijos | C23: =-C12
A24: (-) Bankroll (10%) | C24: =-C16
A25: (-) Ahorro (10%) | C25: =-C17
A26: (-) Caprichos (5%) | C26: =-C18
A27: DISPONIBLE RESTANTE | C27: =SUM(C22:C26)
A28: % Gastado (fijos/ingreso) | C28: =C12/$D$3
A29: Desviacion vs presupuesto | C29: =$D$3-C12
A31: ESTADO DEL PRESUPUESTO
A32: Progreso gastos fijos: | B32: =TEXT(C28,"0.0%")&" del ingreso en gastos fijos"
A33: Disponible restante: | B33: =TEXT(C27,"#,##0.00")&" EUR disponibles este mes"

Sheet CONTROL DE AHORRO
A1: CONTROL DE AHORRO - EVOLUCION ACUMULADA
A2: Fecha | B2: Mes | C2: Anio | D2: Cantidad (EUR) | E2: Acumulado (EUR) | F2: Tasa Ahorro %
A3: 46193 | B3: Junio | C3: 2026 | D3: 200 | E3: 2000 | F3: =D3/'PRESUPUESTO MENSUAL'!$D$3
A6: RESUMEN ANUAL 2026
A7: Total ahorrado anio 2026 | B7: =SUMPRODUCT((ISNUMBER(A3:A1000))*(YEAR(IF(ISNUMBER(A3:A1000),A3:A1000,TODAY()))=2026)*(D3:D1000))
A8: Ahorro mensual medio | B8: =IFERROR(AVERAGEIF(C3:C1000,2026,D3:D1000),0)
A9: Capital acumulado total | B9: =MAX(E3:E1000)
A10: Objetivo anual (10% x 12 meses) | B10: ='PRESUPUESTO MENSUAL'!$D$3*0.10*12
A11: % Cumplimiento | B11: =IFERROR(B8/B10,0)

Sheet CONTROL DE BANKROLL
A1: CONTROL DE BANKROLL - CAPITAL DE TRADING
A2: Fecha | B2: Mes | C2: Anio | D2: Aporte (EUR) | E2: Capital Acumulado (EUR)
A3: 46193 | B3: Junio | C3: 2026 | D3: 200 | E3: 200
A5: RESUMEN
A6: Total bankroll aportado 2026 | B6: =SUMPRODUCT((ISNUMBER(A3:A1000))*(YEAR(IF(ISNUMBER(A3:A1000),A3:A1000,TODAY()))=2026)*(D3:D1000))
A7: Capital acumulado total | B7: =MAX(E3:E1000)
A8: Objetivo anual | B8: ='PRESUPUESTO MENSUAL'!$D$3*0.10*12
A9: % Cumplimiento | B9: =IFERROR(B6/B8,0)

Sheet DASHBOARD DE TRADING
A1: DASHBOARD DE TRADING - RESULTADOS Y ANALISIS
A2: Fecha | B2: Cuenta / Plataforma | C2: Beneficio/Perdida (EUR) | D2: Payout Recibido (EUR) | E2: Observaciones
A3: 46188 | B3: FTMO | C3: 350 | D3: 350 | E3: Cuenta 10K - challenge superado
A5: ESTADISTICAS DE TRADING
A6: Beneficio mensual Jun 2026 | B6: =SUMPRODUCT((ISNUMBER(A3:A1000))*(MONTH(IF(ISNUMBER(A3:A1000),A3:A1000,TODAY()))=6)*(YEAR(IF(ISNUMBER(A3:A1000),A3:A1000,TODAY()))=2026)*(C3:C1000))
A7: Beneficio anual 2026 | B7: =SUMPRODUCT((ISNUMBER(A3:A1000))*(YEAR(IF(ISNUMBER(A3:A1000),A3:A1000,TODAY()))=2026)*(C3:C1000))
A8: Total payouts recibidos | B8: =SUM(D3:D1000)
A9: ROI (sobre bankroll inicial 200 EUR) | B9: =IFERROR(SUM(C3:C1000)/200,0)
A10: Mejor resultado individual | B10: =IFERROR(MAX(C3:C1000),0)
A11: Peor resultado individual | B11: =IFERROR(MIN(C3:C1000),0)
A12: Beneficio acumulado total | B12: =SUM(C3:C1000)
A13: Numero de entradas | B13: =COUNTA(B3:B1000)

Sheet CONTROL DE PAYOUTS
A1: CONTROL DE PAYOUTS - INGRESOS DE TRADING
A2: Fecha | B2: Empresa / Plataforma | C2: Importe (EUR) | D2: Estado | E2: Observaciones
A3: 46188 | B3: FTMO | C3: 350 | D3: Cobrado | E3: Payout junio 2026
A4: 46204 | B4: FTMO | C4: 400 | D4: Pendiente | E4: Payout julio 2026 - estimado
A6: Total cobrado | B6: =SUMIF(D3:D1000,"Cobrado",C3:C1000)
A7: Total pendiente | B7: =SUMIF(D3:D1000,"Pendiente",C3:C1000)
A8: Total anual 2026 | B8: =SUMPRODUCT((ISNUMBER(A3:A1000))*(YEAR(IF(ISNUMBER(A3:A1000),A3:A1000,TODAY()))=2026)*(C3:C1000))
A9: Total historico | B9: =SUM(C3:C1000)

Sheet PATRIMONIO NETO
A1: PATRIMONIO NETO - ACTIVOS Y PASIVOS
A3: ACTIVOS
A4: Concepto | B4: Valor Actual (EUR) | C4: Notas
A5: Cuenta Bancaria Corriente | B5: 500 | C5: Saldo en cuenta corriente
A6: Fondo de Ahorro | B6: 2000 | C6: Ahorro acumulado
A7: Bankroll Trading | B7: 200 | C7: Capital para trading
A8: Capital en Plataformas | B8: 0 | C8: Fondos en brokers/prop firms
A9: Otros Activos | B9: 0 | C9: Otros activos
A10: TOTAL ACTIVOS | B10: =SUM(B5:B9)
A12: PASIVOS / DEUDAS
A13: Concepto | B13: Valor Actual (EUR) | C13: Notas
A14: Deudas personales | B14: 0
A15: Financiaciones pendientes | B15: 0
A16: Otros pasivos | B16: 0
A17: TOTAL PASIVOS | B17: =SUM(B14:B16)
A19: PATRIMONIO NETO
A20: PATRIMONIO NETO = Activos - Pasivos | B20: =B10-B17
A22: EVOLUCION HISTORICA DEL PATRIMONIO
A23: Mes | B23: Activos (EUR) | C23: Pasivos (EUR) | D23: Patrimonio Neto (EUR)
A24: Junio 2026 | B24: 2700 | C24: 0 | D24: =B24-C24

Sheet FONDO DE EMERGENCIA
A1: FONDO DE EMERGENCIA - COBERTURA FINANCIERA
A3: Gastos fijos mensuales | B3: 1575
A4: Objetivo 3 meses | B4: 4725
A5: Objetivo 6 meses (recomendado) | B5: 9450
A6: Objetivo 12 meses (optimo) | B6: 18900
A8: TU FONDO DE EMERGENCIA ACTUAL (edita la celda dorada)
A9: Capital actual fondo emergencia: | B9: 500
A10: Meses cubiertos actualmente | B10: =B9/1575
A11: % cobertura objetivo 6 meses | B11: =B9/9450
A12: % cobertura objetivo 12 meses | B12: =B9/18900
A13: Faltan para 6 meses | B13: =9450-B9
A14: Faltan para 12 meses | B14: =18900-B9
A16: Progreso hacia 6 meses: | B16: =TEXT(MIN(B11,1),"0.0%")&" completado (objetivo: 9,450 EUR)"
A17: Resumen estado: | B17: =IF(B11>=1,"OBJETIVO 6 MESES ALCANZADO",IF(B11>=0.5,"MAS DE LA MITAD COMPLETADO","EN PROGRESO - SIGUE APORTANDO"))
A19: HITOS DEL FONDO DE EMERGENCIA
A20: Objetivo 1 mes: 1,575 EUR
A21: Objetivo 3 meses: 4,725 EUR
A22: Objetivo 6 meses: 9,450 EUR
A23: Objetivo 12 meses: 18,900 EUR

Sheet OBJETIVOS
A1: OBJETIVOS FINANCIEROS ANUALES 2026
A2: Objetivo | B2: Meta Anual (EUR) | C2: Actual (EUR) | D2: Diferencia (EUR) | E2: % Cumplimiento | F2: Estado
A3: Ahorro anual | B3: 2400 | C3: 200 | D3: =C3-B3 | E3: =IFERROR(C3/B3,0) | F3: =TEXT(IFERROR(C3/B3,0),"0.0%")&IF(IFERROR(C3/B3,0)>=1," COMPLETADO",IF(IFERROR(C3/B3,0)>=0.5," EN BUEN CAMINO"," EN PROGRESO"))
A4: Bankroll anual | B4: 2400 | C4: 200 | D4: =C4-B4 | E4: =IFERROR(C4/B4,0) | F4: =TEXT(IFERROR(C4/B4,0),"0.0%")&IF(IFERROR(C4/B4,0)>=1," COMPLETADO",IF(IFERROR(C4/B4,0)>=0.5," EN BUEN CAMINO"," EN PROGRESO"))
A5: Patrimonio anual | B5: 5000 | C5: 2700 | D5: =C5-B5 | E5: =IFERROR(C5/B5,0) | F5: =TEXT(IFERROR(C5/B5,0),"0.0%")&IF(IFERROR(C5/B5,0)>=1," COMPLETADO",IF(IFERROR(C5/B5,0)>=0.5," EN BUEN CAMINO"," EN PROGRESO"))
A6: Beneficios trading | B6: 4200 | C6: 350 | D6: =C6-B6 | E6: =IFERROR(C6/B6,0) | F6: =TEXT(IFERROR(C6/B6,0),"0.0%")&IF(IFERROR(C6/B6,0)>=1," COMPLETADO",IF(IFERROR(C6/B6,0)>=0.5," EN BUEN CAMINO"," EN PROGRESO"))

Sheet GASTOS HORMIGA
A1: GASTOS HORMIGA - CONTROL DE PEQUENOS GASTOS
A2: Fecha | B2: Mes | C2: Categoria | D2: Descripcion | E2: Importe (EUR) | F2: % Ingreso | G2: Alerta
A3: 46183 | B3: Junio | C3: Restaurantes | D3: Restaurante familiar | E3: 35 | F3: =E3/'PRESUPUESTO MENSUAL'!$D$3 | G3: =IF(E3/'PRESUPUESTO MENSUAL'!$D$3>0.05,"ALERTA","OK")
A4: 46185 | B4: Junio | C4: Amazon | D4: Compra Amazon impulsiva | E4: 28.5 | F4: =E4/'PRESUPUESTO MENSUAL'!$D$3 | G4: =IF(E4/'PRESUPUESTO MENSUAL'!$D$3>0.05,"ALERTA","OK")
A5: 46187 | B5: Junio | C5: Ocio | D5: Cine + palomitas | E5: 18 | F5: =E5/'PRESUPUESTO MENSUAL'!$D$3 | G5: =IF(E5/'PRESUPUESTO MENSUAL'!$D$3>0.05,"ALERTA","OK")
A6: 46191 | B6: Junio | C6: Suscripciones | D6: Netflix | E6: 13.99 | F6: =E6/'PRESUPUESTO MENSUAL'!$D$3 | G6: =IF(E6/'PRESUPUESTO MENSUAL'!$D$3>0.05,"ALERTA","OK")
A7: 46195 | B7: Junio | C7: Compras impulsivas | D7: Ropa | E7: 45 | F7: =E7/'PRESUPUESTO MENSUAL'!$D$3 | G7: =IF(E7/'PRESUPUESTO MENSUAL'!$D$3>0.05,"ALERTA","OK")
A502: RESUMEN POR CATEGORIA - JUNIO 2026
A503: Categoria | B503: Total Mes (EUR) | C503: % Ingreso | D503: Limite 5% | E503: Estado
A504: Restaurantes | B504: =SUMIF($C$3:$C$500,$A504,$E$3:$E$500) | C504: =B504/'PRESUPUESTO MENSUAL'!$D$3 | D504: 5% limite | E504: =IF(B504>'PRESUPUESTO MENSUAL'!$D$3*0.05,"EXCEDIDO","OK")
A505: Amazon | B505: =SUMIF($C$3:$C$500,$A505,$E$3:$E$500) | C505: =B505/'PRESUPUESTO MENSUAL'!$D$3 | D505: 5% limite | E505: =IF(B505>'PRESUPUESTO MENSUAL'!$D$3*0.05,"EXCEDIDO","OK")
A506: Ocio | B506: =SUMIF($C$3:$C$500,$A506,$E$3:$E$500) | C506: =B506/'PRESUPUESTO MENSUAL'!$D$3 | D506: 5% limite | E506: =IF(B506>'PRESUPUESTO MENSUAL'!$D$3*0.05,"EXCEDIDO","OK")
A507: Suscripciones | B507: =SUMIF($C$3:$C$500,$A507,$E$3:$E$500) | C507: =B507/'PRESUPUESTO MENSUAL'!$D$3 | D507: 5% limite | E507: =IF(B507>'PRESUPUESTO MENSUAL'!$D$3*0.05,"EXCEDIDO","OK")
A508: Compras impulsivas | B508: =SUMIF($C$3:$C$500,$A508,$E$3:$E$500) | C508: =B508/'PRESUPUESTO MENSUAL'!$D$3 | D508: 5% limite | E508: =IF(B508>'PRESUPUESTO MENSUAL'!$D$3*0.05,"EXCEDIDO","OK")

Sheet RANKING MEJORES MESES
A1: RANKING DE MEJORES MESES - TOP 5 HISTORICO
A3: MEJORES MESES - INGRESOS | D3: MEJORES MESES - AHORRO | G3: MEJORES MESES - TRADING
A4: Posicion | B4: Mes | C4: Importe | D4: Posicion | E4: Mes | F4: Importe | G4: Posicion | H4: Mes | I4: Importe
A5: 1ro | B5: Junio 2026 | C5: 2350 | D5: 1ro | E5: Junio 2026 | F5: 2350 | G5: 1ro | H5: Junio 2026 | I5: 2350
A6: 2do | B6: - | C6: 0 | D6: 2do | E6: - | F6: 0 | G6: 2do | H6: - | I6: 0
A7: 3ro | B7: - | C7: 0 | D7: 3ro | E7: - | F7: 0 | G7: 3ro | H7: - | I7: 0
A8: 4to | B8: - | C8: 0 | D8: 4to | E8: - | F8: 0 | G8: 4to | H8: - | I8: 0
A9: 5to | B9: - | C9: 0 | D9: 5to | E9: - | F9: 0 | G9: 5to | H9: - | I9: 0
A12: NOTA: Actualiza manualmente los valores de este ranking con tus datos mensuales.

Sheet LIBERTAD FINANCIERA
A1: LIBERTAD FINANCIERA - COBERTURA CON TRADING
A3: Gastos mensuales fijos | B3: 1575
A4: Beneficio medio mensual trading (editar) | B4: 350
A5: % Cobertura actual | B5: =B4/B3
A6: Meses con datos de trading | B6: 1
A8: Progreso libertad financiera: | B8: =TEXT(MIN(B5,1),"0.0%")&" de cobertura de gastos con trading"
A9: Estado actual: | B9: ="El trading cubre el "&TEXT(B5,"0.0%")&" de tus gastos mensuales fijos"
A11: HITOS DE LIBERTAD FINANCIERA
A12: 25% | B12: 25% - Inicio del camino: trading cubre 1/4 de gastos
A13: 50% | B13: 50% - Punto medio: trading cubre la mitad de gastos
A14: 75% | B14: 75% - Casi libre: solo 25% depende del empleo
A15: 100% | B15: 100% - LIBERTAD FINANCIERA: trading cubre todos los gastos

Sheet PROYECCIONES FUTURAS
A1: PROYECCIONES FUTURAS - 1, 3 Y 5 ANOS
A3: PARAMETROS DE ENTRADA (edita las celdas doradas)
A4: Ingreso medio mensual neto | B4: 2000
A5: Tasa de ahorro mensual % | B5: 0.1
A6: Beneficio medio mensual trading | B6: 350
A7: Rentabilidad anual inversion % | B7: 0.05
A8: Aportacion bankroll mensual | B8: 200
A10: TABLA DE PROYECCIONES
A11: Anio | B11: Ahorro Acum. (EUR) | C11: Bankroll (EUR) | D11: Patrimonio Total (EUR) | E11: Benef. Trading Acum. (EUR) | F11: Libertad Fin. %
A12: Anio 1 | B12: =$B$4*$B$5*12*1 | C12: =$B$8*12*1 | D12: =B12+C12 | E12: =$B$6*12*1 | F12: =IFERROR($B$6/1575,0)
A13: Anio 2 | B13: =$B$4*$B$5*12*2 | C13: =$B$8*12*2 | D13: =B13+C13 | E13: =$B$6*12*2 | F13: =IFERROR($B$6/1575,0)
A14: Anio 3 | B14: =$B$4*$B$5*12*3 | C14: =$B$8*12*3 | D14: =B14+C14 | E14: =$B$6*12*3 | F14: =IFERROR($B$6/1575,0)
A15: Anio 4 | B15: =$B$4*$B$5*12*4 | C15: =$B$8*12*4 | D15: =B15+C15 | E15: =$B$6*12*4 | F15: =IFERROR($B$6/1575,0)
A16: Anio 5 | B16: =$B$4*$B$5*12*5 | C16: =$B$8*12*5 | D16: =B16+C16 | E16: =$B$6*12*5 | F16: =IFERROR($B$6/1575,0)

Sheet SCORE DEL TRADER
A1: SCORE DEL TRADER - EVALUACION INTEGRAL 0-100
A3: COMPONENTES DEL SCORE
A4: Componente | B4: Peso | C4: Descripcion | D4: Puntos (max 20)
A5: Cumplimiento Ahorro | B5: 20 pts | C5: 200/2400 = 8.3% completado | D5: =MIN(20,IFERROR(200/2400*20,0))
A6: Cumplimiento Bankroll | B6: 20 pts | C6: 200/2400 = 8.3% completado | D6: =MIN(20,IFERROR(200/2400*20,0))
A7: Control de Gastos | B7: 20 pts | C7: Gastos vs ingreso mensual | D7: =IF(1575<=2000,20,MAX(0,20-((1575-2000)/2000)*20))
A8: Crecimiento Patrimonio | B8: 20 pts | C8: 2700/5000 objetivo | D8: =MIN(20,IFERROR(2700/5000*20,0))
A9: Resultados Trading | B9: 20 pts | C9: 350/2000 objetivo anual | D9: =MIN(20,IFERROR(350/2000*20,0))
A10: SCORE TOTAL DEL TRADER (sobre 100) | D10: =ROUND(SUM(D5:D9),1)
A12: SEMAFORO DE EVALUACION
A13: SCORE >= 70 - EXCELENTE: Vas por buen camino, manten el ritmo
A14: SCORE 40-69 - MEJORABLE: Hay areas que necesitan atencion
A15: SCORE < 40 - ALERTA: Revisa tu estrategia financiera
A17: Tu evaluacion: | B17: =IF(D10>=70,"EXCELENTE - Score: "&TEXT(D10,"0.0")&"/100",IF(D10>=40,"MEJORABLE - Score: "&TEXT(D10,"0.0")&"/100","ALERTA - Score: "&TEXT(D10,"0.0")&"/100"))
